nanoprep_tools/__init__.py
nanoprep_tools/fq_src_mapping.py
nanoprep_tools/nanopreptools.py
nanoprep-0.1.9.1.dist-info/LICENSE
nanoprep-0.1.9.1.dist-info/METADATA
nanoprep-0.1.9.1.dist-info/WHEEL
nanoprep-0.1.9.1.dist-info/top_level.txt
nanoprep-0.1.9.1.dist-info/RECORD
