Metadata-Version: 2.1
Name: nanoprep
Version: 0.1.9.1
Summary: Provides tools to preprocess nanopore amplicon reads more flexibly
Home-page: https://github.com/xpli2020/NanoPrep.git
Author: Xiaoping Li
Author-email: lixiaopi@vt.edu
Project-URL: Bug Tracker, https://github.com/xpli2020/NanoPrep.git/issues
Classifier: Programming Language :: Python :: 3
Classifier: License :: OSI Approved :: MIT License
Classifier: Operating System :: OS Independent
Requires-Python: >=3.6
License-File: LICENSE
Requires-Dist: pandas
Requires-Dist: biopython
